odoo/addons/contract_commission/README.rst
odoo/addons/contract_commission/__init__.py
odoo/addons/contract_commission/__manifest__.py
odoo/addons/contract_commission/i18n/ca.po
odoo/addons/contract_commission/i18n/contract_commission.pot
odoo/addons/contract_commission/i18n/de.po
odoo/addons/contract_commission/i18n/el_GR.po
odoo/addons/contract_commission/i18n/es.po
odoo/addons/contract_commission/i18n/es_MX.po
odoo/addons/contract_commission/i18n/fr.po
odoo/addons/contract_commission/i18n/it.po
odoo/addons/contract_commission/i18n/pt_BR.po
odoo/addons/contract_commission/i18n/sl.po
odoo/addons/contract_commission/models/__init__.py
odoo/addons/contract_commission/models/contract_line.py
odoo/addons/contract_commission/readme/CONFIGURE.rst
odoo/addons/contract_commission/readme/CONTRIBUTORS.rst
odoo/addons/contract_commission/readme/DESCRIPTION.rst
odoo/addons/contract_commission/readme/USAGE.rst
odoo/addons/contract_commission/static/description/banner.png
odoo/addons/contract_commission/static/description/icon.png
odoo/addons/contract_commission/static/description/icon.svg
odoo/addons/contract_commission/static/description/index.html
odoo/addons/contract_commission/tests/__init__.py
odoo/addons/contract_commission/tests/test_contract_commission.py
odoo12_addon_contract_commission-12.0.1.0.1.dist-info/METADATA
odoo12_addon_contract_commission-12.0.1.0.1.dist-info/WHEEL
odoo12_addon_contract_commission-12.0.1.0.1.dist-info/top_level.txt
odoo12_addon_contract_commission-12.0.1.0.1.dist-info/RECORD
